{"cameraMode":{"drawMode":0,"name":"Shaded","section":"Shading Mode"},"sceneLighting":false,"audioPlay":false,"sceneViewState":{"m_AlwaysRefresh":false,"showFog":true,"showSkybox":false,"showFlares":true,"showImageEffects":true,"showParticleSystems":true,"showVisualEffectGraphs":true,"m_FxEnabled":true},"in2DMode":false,"pivot":{"x":-4.090000152587891,"y":1.25,"z":0.0},"rotation":{"x":-0.005846803542226553,"y":0.9688109755516052,"z":-0.246665820479393,"w":-0.022964205592870714},"size":1.6859716176986695,"orthographic":false}